versacore/__init__.py
versacore/browserless.py
versacore/llm_chat_api.py
versacore/webArticleSummariseQuery.py
VersaCore-0.1.0.dist-info/METADATA
VersaCore-0.1.0.dist-info/WHEEL
VersaCore-0.1.0.dist-info/top_level.txt
VersaCore-0.1.0.dist-info/RECORD
